pyvalve/__init__.py
pyvalve-0.1.3.dist-info/LICENSE
pyvalve-0.1.3.dist-info/WHEEL
pyvalve-0.1.3.dist-info/METADATA
pyvalve-0.1.3.dist-info/RECORD
