Metadata-Version: 2.1
Name: pyvalve
Version: 0.1.3
Summary: Asyncio python clamav client
Home-page: https://github.com/bradsacks99/pyvalve
License: GPL-3.0-only
Author: Bradley Sacks
Author-email: bradsacks99@gmail.com
Requires-Python: >=3.8,<4.0
Classifier: License :: OSI Approved :: GNU General Public License v3 (GPLv3)
Classifier: Programming Language :: Python :: 3
Classifier: Programming Language :: Python :: 3.10
Classifier: Programming Language :: Python :: 3.8
Classifier: Programming Language :: Python :: 3.9
Requires-Dist: aiofile (>=3.8.1,<4.0.0)
Requires-Dist: aiopathlib (>=0.5.0,<0.6.0)
Requires-Dist: asyncinit (>=0.2.4,<0.3.0)
Project-URL: Documentation, https://github.com/bradsacks99/pyvalve/blob/master/README.md
